adafruit_circuitpython_typing-1.12.0.dist-info/licenses/LICENSE
circuitpython_typing/__init__.py
circuitpython_typing/device_drivers.py
circuitpython_typing/displayio.py
circuitpython_typing/http.py
circuitpython_typing/io.py
circuitpython_typing/led.py
circuitpython_typing/pil.py
circuitpython_typing/pwmio.py
circuitpython_typing/py.typed
circuitpython_typing/socket.py
adafruit_circuitpython_typing-1.12.0.dist-info/METADATA
adafruit_circuitpython_typing-1.12.0.dist-info/WHEEL
adafruit_circuitpython_typing-1.12.0.dist-info/top_level.txt
adafruit_circuitpython_typing-1.12.0.dist-info/RECORD
