Metadata-Version: 2.4
Name: adafruit-circuitpython-typing
Version: 1.12.0
Summary: Types needed for type annotation that are not in `typing`
Author-email: Adafruit Industries <circuitpython@adafruit.com>
License: MIT
Project-URL: Homepage, https://github.com/adafruit/Adafruit_CircuitPython_Typing
Keywords: adafruit,blinka,circuitpython,micropython,circuitpython_typing
Classifier: Intended Audience :: Developers
Classifier: Topic :: Software Development :: Libraries
Classifier: Topic :: Software Development :: Embedded Systems
Classifier: Topic :: System :: Hardware
Classifier: License :: OSI Approved :: MIT License
Classifier: Programming Language :: Python :: 3
Requires-Python: >=3.8
License-File: LICENSE
Requires-Dist: Adafruit-Blinka
Requires-Dist: adafruit-circuitpython-busdevice
Requires-Dist: adafruit-circuitpython-requests
Requires-Dist: typing_extensions~=4.0
Provides-Extra: optional
Dynamic: license-file
